MANIFEST.in
README.md
VERSION.txt
setup.cfg
setup.py
protobuf_qtypes.egg-info/PKG-INFO
protobuf_qtypes.egg-info/SOURCES.txt
protobuf_qtypes.egg-info/dependency_links.txt
protobuf_qtypes.egg-info/not-zip-safe
protobuf_qtypes.egg-info/requires.txt
protobuf_qtypes.egg-info/top_level.txt
qtypes/__init__.py
qtypes/qtypes_pb2.py