Metadata-Version: 1.1
Name: protobuf-qtypes
Version: 0.3.6
Summary: qtypes data structures
Home-page: http://github.com/piotrkowalczuk/qtypes
Author: Piotr Kowalczuk
Author-email: p.kowalczuk.priv@gmail.com
License: MIT
Download-URL: https://github.com/piotrkowalczuk/qtypes/archive/v0.3.6.tar.gz
Keywords: protobuf,data-structures
Platform: UNKNOWN
